{
	"user_id": "16",
	"task_id": "pilot2_left",
	"creation_time": 1622735553,
	"modified_time": 1622738845,
	"status": "completed",
	"alphabet": [
		"z",
		"y",
		"f",
		"c",
		"k",
		"n",
		"w",
		"m",
		"b",
		"q",
		"i",
		"u",
		"j",
		"a",
		"e"
	],
	"object_array": [
		3,
		0,
		4,
		1,
		5,
		6,
		2,
		7
	],
	"trial_sequence": [
		{
			"event": "consent",
			"payload": {
				"session_time": 23,
				"basic_pay": 300,
				"max_pay": 404,
				"progress": 0
			}
		},
		{
			"event": "calibration",
			"payload": {
				"progress": 0.011111111111111112
			}
		},
		{
			"event": "distance_instructions",
			"payload": {
				"progress": 0.03333333333333333
			}
		},
		{
			"event": "training_instructions",
			"payload": {
				"instruction_time": 10000,
				"progress": 0.044444444444444446
			}
		},
		{
			"event": "training_block",
			"payload": {
				"training_trials": [
					{
						"word": [
							13,
							9,
							6,
							2,
							0
						],
						"object": 6
					},
					{
						"word": [
							12,
							8,
							3,
							1,
							0
						],
						"object": 1
					},
					{
						"word": [
							14,
							10,
							6,
							2,
							0
						],
						"object": 7
					},
					{
						"word": [
							11,
							7,
							5,
							2,
							0
						],
						"object": 4
					}
				],
				"test_trial": {
					"word": [
						14,
						10,
						6,
						2,
						0
					],
					"object": 7
				},
				"trial_time": 2000,
				"pause_time": 500,
				"show_flankers": true,
				"progress": 0.06666666666666667
			}
		},
		{
			"event": "training_block",
			"payload": {
				"training_trials": [
					{
						"word": [
							12,
							8,
							5,
							2,
							0
						],
						"object": 5
					},
					{
						"word": [
							14,
							10,
							4,
							1,
							0
						],
						"object": 3
					},
					{
						"word": [
							13,
							9,
							4,
							1,
							0
						],
						"object": 2
					},
					{
						"word": [
							11,
							7,
							3,
							1,
							0
						],
						"object": 0
					}
				],
				"test_trial": {
					"word": [
						11,
						7,
						5,
						2,
						0
					],
					"object": 4
				},
				"trial_time": 2000,
				"pause_time": 500,
				"show_flankers": true,
				"progress": 0.07777777777777778
			}
		},
		{
			"event": "training_block",
			"payload": {
				"training_trials": [
					{
						"word": [
							14,
							10,
							6,
							2,
							0
						],
						"object": 7
					},
					{
						"word": [
							14,
							10,
							4,
							1,
							0
						],
						"object": 3
					},
					{
						"word": [
							12,
							8,
							5,
							2,
							0
						],
						"object": 5
					},
					{
						"word": [
							13,
							9,
							6,
							2,
							0
						],
						"object": 6
					}
				],
				"test_trial": {
					"word": [
						14,
						10,
						4,
						1,
						0
					],
					"object": 3
				},
				"trial_time": 2000,
				"pause_time": 500,
				"show_flankers": true,
				"progress": 0.08888888888888889
			}
		},
		{
			"event": "training_block",
			"payload": {
				"training_trials": [
					{
						"word": [
							12,
							8,
							3,
							1,
							0
						],
						"object": 1
					},
					{
						"word": [
							11,
							7,
							5,
							2,
							0
						],
						"object": 4
					},
					{
						"word": [
							13,
							9,
							4,
							1,
							0
						],
						"object": 2
					},
					{
						"word": [
							11,
							7,
							3,
							1,
							0
						],
						"object": 0
					}
				],
				"test_trial": {
					"word": [
						13,
						9,
						4,
						1,
						0
					],
					"object": 2
				},
				"trial_time": 2000,
				"pause_time": 500,
				"show_flankers": true,
				"progress": 0.1
			}
		},
		{
			"event": "training_block",
			"payload": {
				"training_trials": [
					{
						"word": [
							13,
							9,
							6,
							2,
							0
						],
						"object": 6
					},
					{
						"word": [
							12,
							8,
							3,
							1,
							0
						],
						"object": 1
					},
					{
						"word": [
							11,
							7,
							5,
							2,
							0
						],
						"object": 4
					},
					{
						"word": [
							11,
							7,
							3,
							1,
							0
						],
						"object": 0
					}
				],
				"test_trial": {
					"word": [
						12,
						8,
						3,
						1,
						0
					],
					"object": 1
				},
				"trial_time": 2000,
				"pause_time": 500,
				"show_flankers": true,
				"progress": 0.1111111111111111
			}
		},
		{
			"event": "training_block",
			"payload": {
				"training_trials": [
					{
						"word": [
							13,
							9,
							4,
							1,
							0
						],
						"object": 2
					},
					{
						"word": [
							14,
							10,
							6,
							2,
							0
						],
						"object": 7
					},
					{
						"word": [
							12,
							8,
							5,
							2,
							0
						],
						"object": 5
					},
					{
						"word": [
							14,
							10,
							4,
							1,
							0
						],
						"object": 3
					}
				],
				"test_trial": {
					"word": [
						13,
						9,
						6,
						2,
						0
					],
					"object": 6
				},
				"trial_time": 2000,
				"pause_time": 500,
				"show_flankers": true,
				"progress": 0.12222222222222222
			}
		},
		{
			"event": "training_block",
			"payload": {
				"training_trials": [
					{
						"word": [
							14,
							10,
							6,
							2,
							0
						],
						"object": 7
					},
					{
						"word": [
							11,
							7,
							5,
							2,
							0
						],
						"object": 4
					},
					{
						"word": [
							12,
							8,
							3,
							1,
							0
						],
						"object": 1
					},
					{
						"word": [
							13,
							9,
							6,
							2,
							0
						],
						"object": 6
					}
				],
				"test_trial": {
					"word": [
						11,
						7,
						3,
						1,
						0
					],
					"object": 0
				},
				"trial_time": 2000,
				"pause_time": 500,
				"show_flankers": true,
				"progress": 0.13333333333333333
			}
		},
		{
			"event": "training_block",
			"payload": {
				"training_trials": [
					{
						"word": [
							11,
							7,
							3,
							1,
							0
						],
						"object": 0
					},
					{
						"word": [
							12,
							8,
							5,
							2,
							0
						],
						"object": 5
					},
					{
						"word": [
							13,
							9,
							4,
							1,
							0
						],
						"object": 2
					},
					{
						"word": [
							14,
							10,
							4,
							1,
							0
						],
						"object": 3
					}
				],
				"test_trial": {
					"word": [
						12,
						8,
						5,
						2,
						0
					],
					"object": 5
				},
				"trial_time": 2000,
				"pause_time": 500,
				"show_flankers": true,
				"progress": 0.14444444444444443
			}
		},
		{
			"event": "training_block",
			"payload": {
				"training_trials": [
					{
						"word": [
							14,
							10,
							4,
							1,
							0
						],
						"object": 3
					},
					{
						"word": [
							12,
							8,
							5,
							2,
							0
						],
						"object": 5
					},
					{
						"word": [
							12,
							8,
							3,
							1,
							0
						],
						"object": 1
					},
					{
						"word": [
							13,
							9,
							6,
							2,
							0
						],
						"object": 6
					}
				],
				"test_trial": {
					"word": [
						12,
						8,
						5,
						2,
						0
					],
					"object": 5
				},
				"trial_time": 2000,
				"pause_time": 500,
				"show_flankers": true,
				"progress": 0.15555555555555556
			}
		},
		{
			"event": "training_block",
			"payload": {
				"training_trials": [
					{
						"word": [
							11,
							7,
							3,
							1,
							0
						],
						"object": 0
					},
					{
						"word": [
							13,
							9,
							4,
							1,
							0
						],
						"object": 2
					},
					{
						"word": [
							11,
							7,
							5,
							2,
							0
						],
						"object": 4
					},
					{
						"word": [
							14,
							10,
							6,
							2,
							0
						],
						"object": 7
					}
				],
				"test_trial": {
					"word": [
						11,
						7,
						3,
						1,
						0
					],
					"object": 0
				},
				"trial_time": 2000,
				"pause_time": 500,
				"show_flankers": true,
				"progress": 0.16666666666666666
			}
		},
		{
			"event": "training_block",
			"payload": {
				"training_trials": [
					{
						"word": [
							11,
							7,
							3,
							1,
							0
						],
						"object": 0
					},
					{
						"word": [
							14,
							10,
							4,
							1,
							0
						],
						"object": 3
					},
					{
						"word": [
							14,
							10,
							6,
							2,
							0
						],
						"object": 7
					},
					{
						"word": [
							12,
							8,
							3,
							1,
							0
						],
						"object": 1
					}
				],
				"test_trial": {
					"word": [
						13,
						9,
						4,
						1,
						0
					],
					"object": 2
				},
				"trial_time": 2000,
				"pause_time": 500,
				"show_flankers": true,
				"progress": 0.17777777777777778
			}
		},
		{
			"event": "training_block",
			"payload": {
				"training_trials": [
					{
						"word": [
							11,
							7,
							5,
							2,
							0
						],
						"object": 4
					},
					{
						"word": [
							13,
							9,
							6,
							2,
							0
						],
						"object": 6
					},
					{
						"word": [
							13,
							9,
							4,
							1,
							0
						],
						"object": 2
					},
					{
						"word": [
							12,
							8,
							5,
							2,
							0
						],
						"object": 5
					}
				],
				"test_trial": {
					"word": [
						13,
						9,
						6,
						2,
						0
					],
					"object": 6
				},
				"trial_time": 2000,
				"pause_time": 500,
				"show_flankers": true,
				"progress": 0.18888888888888888
			}
		},
		{
			"event": "training_block",
			"payload": {
				"training_trials": [
					{
						"word": [
							13,
							9,
							6,
							2,
							0
						],
						"object": 6
					},
					{
						"word": [
							12,
							8,
							5,
							2,
							0
						],
						"object": 5
					},
					{
						"word": [
							11,
							7,
							5,
							2,
							0
						],
						"object": 4
					},
					{
						"word": [
							14,
							10,
							6,
							2,
							0
						],
						"object": 7
					}
				],
				"test_trial": {
					"word": [
						12,
						8,
						3,
						1,
						0
					],
					"object": 1
				},
				"trial_time": 2000,
				"pause_time": 500,
				"show_flankers": true,
				"progress": 0.2
			}
		},
		{
			"event": "training_block",
			"payload": {
				"training_trials": [
					{
						"word": [
							11,
							7,
							3,
							1,
							0
						],
						"object": 0
					},
					{
						"word": [
							12,
							8,
							3,
							1,
							0
						],
						"object": 1
					},
					{
						"word": [
							13,
							9,
							4,
							1,
							0
						],
						"object": 2
					},
					{
						"word": [
							14,
							10,
							4,
							1,
							0
						],
						"object": 3
					}
				],
				"test_trial": {
					"word": [
						11,
						7,
						5,
						2,
						0
					],
					"object": 4
				},
				"trial_time": 2000,
				"pause_time": 500,
				"show_flankers": true,
				"progress": 0.2111111111111111
			}
		},
		{
			"event": "training_block",
			"payload": {
				"training_trials": [
					{
						"word": [
							13,
							9,
							6,
							2,
							0
						],
						"object": 6
					},
					{
						"word": [
							11,
							7,
							5,
							2,
							0
						],
						"object": 4
					},
					{
						"word": [
							12,
							8,
							3,
							1,
							0
						],
						"object": 1
					},
					{
						"word": [
							14,
							10,
							6,
							2,
							0
						],
						"object": 7
					}
				],
				"test_trial": {
					"word": [
						14,
						10,
						6,
						2,
						0
					],
					"object": 7
				},
				"trial_time": 2000,
				"pause_time": 500,
				"show_flankers": true,
				"progress": 0.2222222222222222
			}
		},
		{
			"event": "training_block",
			"payload": {
				"training_trials": [
					{
						"word": [
							13,
							9,
							4,
							1,
							0
						],
						"object": 2
					},
					{
						"word": [
							12,
							8,
							5,
							2,
							0
						],
						"object": 5
					},
					{
						"word": [
							11,
							7,
							3,
							1,
							0
						],
						"object": 0
					},
					{
						"word": [
							14,
							10,
							4,
							1,
							0
						],
						"object": 3
					}
				],
				"test_trial": {
					"word": [
						14,
						10,
						4,
						1,
						0
					],
					"object": 3
				},
				"trial_time": 2000,
				"pause_time": 500,
				"show_flankers": true,
				"progress": 0.23333333333333334
			}
		},
		{
			"event": "training_block",
			"payload": {
				"training_trials": [
					{
						"word": [
							12,
							8,
							5,
							2,
							0
						],
						"object": 5
					},
					{
						"word": [
							14,
							10,
							6,
							2,
							0
						],
						"object": 7
					},
					{
						"word": [
							14,
							10,
							4,
							1,
							0
						],
						"object": 3
					},
					{
						"word": [
							11,
							7,
							5,
							2,
							0
						],
						"object": 4
					}
				],
				"test_trial": {
					"word": [
						14,
						10,
						6,
						2,
						0
					],
					"object": 7
				},
				"trial_time": 2000,
				"pause_time": 500,
				"show_flankers": true,
				"progress": 0.24444444444444444
			}
		},
		{
			"event": "training_block",
			"payload": {
				"training_trials": [
					{
						"word": [
							11,
							7,
							3,
							1,
							0
						],
						"object": 0
					},
					{
						"word": [
							13,
							9,
							4,
							1,
							0
						],
						"object": 2
					},
					{
						"word": [
							12,
							8,
							3,
							1,
							0
						],
						"object": 1
					},
					{
						"word": [
							13,
							9,
							6,
							2,
							0
						],
						"object": 6
					}
				],
				"test_trial": {
					"word": [
						13,
						9,
						4,
						1,
						0
					],
					"object": 2
				},
				"trial_time": 2000,
				"pause_time": 500,
				"show_flankers": true,
				"progress": 0.25555555555555554
			}
		},
		{
			"event": "training_block",
			"payload": {
				"training_trials": [
					{
						"word": [
							13,
							9,
							6,
							2,
							0
						],
						"object": 6
					},
					{
						"word": [
							11,
							7,
							5,
							2,
							0
						],
						"object": 4
					},
					{
						"word": [
							11,
							7,
							3,
							1,
							0
						],
						"object": 0
					},
					{
						"word": [
							13,
							9,
							4,
							1,
							0
						],
						"object": 2
					}
				],
				"test_trial": {
					"word": [
						12,
						8,
						3,
						1,
						0
					],
					"object": 1
				},
				"trial_time": 2000,
				"pause_time": 500,
				"show_flankers": true,
				"progress": 0.26666666666666666
			}
		},
		{
			"event": "training_block",
			"payload": {
				"training_trials": [
					{
						"word": [
							12,
							8,
							3,
							1,
							0
						],
						"object": 1
					},
					{
						"word": [
							12,
							8,
							5,
							2,
							0
						],
						"object": 5
					},
					{
						"word": [
							14,
							10,
							6,
							2,
							0
						],
						"object": 7
					},
					{
						"word": [
							14,
							10,
							4,
							1,
							0
						],
						"object": 3
					}
				],
				"test_trial": {
					"word": [
						14,
						10,
						4,
						1,
						0
					],
					"object": 3
				},
				"trial_time": 2000,
				"pause_time": 500,
				"show_flankers": true,
				"progress": 0.2777777777777778
			}
		},
		{
			"event": "training_block",
			"payload": {
				"training_trials": [
					{
						"word": [
							11,
							7,
							3,
							1,
							0
						],
						"object": 0
					},
					{
						"word": [
							12,
							8,
							3,
							1,
							0
						],
						"object": 1
					},
					{
						"word": [
							12,
							8,
							5,
							2,
							0
						],
						"object": 5
					},
					{
						"word": [
							14,
							10,
							6,
							2,
							0
						],
						"object": 7
					}
				],
				"test_trial": {
					"word": [
						11,
						7,
						3,
						1,
						0
					],
					"object": 0
				},
				"trial_time": 2000,
				"pause_time": 500,
				"show_flankers": true,
				"progress": 0.28888888888888886
			}
		},
		{
			"event": "training_block",
			"payload": {
				"training_trials": [
					{
						"word": [
							13,
							9,
							4,
							1,
							0
						],
						"object": 2
					},
					{
						"word": [
							14,
							10,
							4,
							1,
							0
						],
						"object": 3
					},
					{
						"word": [
							13,
							9,
							6,
							2,
							0
						],
						"object": 6
					},
					{
						"word": [
							11,
							7,
							5,
							2,
							0
						],
						"object": 4
					}
				],
				"test_trial": {
					"word": [
						12,
						8,
						5,
						2,
						0
					],
					"object": 5
				},
				"trial_time": 2000,
				"pause_time": 500,
				"show_flankers": true,
				"progress": 0.3
			}
		},
		{
			"event": "training_block",
			"payload": {
				"training_trials": [
					{
						"word": [
							12,
							8,
							5,
							2,
							0
						],
						"object": 5
					},
					{
						"word": [
							11,
							7,
							5,
							2,
							0
						],
						"object": 4
					},
					{
						"word": [
							12,
							8,
							3,
							1,
							0
						],
						"object": 1
					},
					{
						"word": [
							13,
							9,
							4,
							1,
							0
						],
						"object": 2
					}
				],
				"test_trial": {
					"word": [
						13,
						9,
						6,
						2,
						0
					],
					"object": 6
				},
				"trial_time": 2000,
				"pause_time": 500,
				"show_flankers": true,
				"progress": 0.3111111111111111
			}
		},
		{
			"event": "training_block",
			"payload": {
				"training_trials": [
					{
						"word": [
							13,
							9,
							6,
							2,
							0
						],
						"object": 6
					},
					{
						"word": [
							11,
							7,
							3,
							1,
							0
						],
						"object": 0
					},
					{
						"word": [
							14,
							10,
							4,
							1,
							0
						],
						"object": 3
					},
					{
						"word": [
							14,
							10,
							6,
							2,
							0
						],
						"object": 7
					}
				],
				"test_trial": {
					"word": [
						11,
						7,
						5,
						2,
						0
					],
					"object": 4
				},
				"trial_time": 2000,
				"pause_time": 500,
				"show_flankers": true,
				"progress": 0.32222222222222224
			}
		},
		{
			"event": "training_block",
			"payload": {
				"training_trials": [
					{
						"word": [
							12,
							8,
							5,
							2,
							0
						],
						"object": 5
					},
					{
						"word": [
							14,
							10,
							4,
							1,
							0
						],
						"object": 3
					},
					{
						"word": [
							14,
							10,
							6,
							2,
							0
						],
						"object": 7
					},
					{
						"word": [
							11,
							7,
							5,
							2,
							0
						],
						"object": 4
					}
				],
				"test_trial": {
					"word": [
						14,
						10,
						4,
						1,
						0
					],
					"object": 3
				},
				"trial_time": 2000,
				"pause_time": 500,
				"show_flankers": true,
				"progress": 0.3333333333333333
			}
		},
		{
			"event": "training_block",
			"payload": {
				"training_trials": [
					{
						"word": [
							13,
							9,
							6,
							2,
							0
						],
						"object": 6
					},
					{
						"word": [
							11,
							7,
							3,
							1,
							0
						],
						"object": 0
					},
					{
						"word": [
							13,
							9,
							4,
							1,
							0
						],
						"object": 2
					},
					{
						"word": [
							12,
							8,
							3,
							1,
							0
						],
						"object": 1
					}
				],
				"test_trial": {
					"word": [
						12,
						8,
						3,
						1,
						0
					],
					"object": 1
				},
				"trial_time": 2000,
				"pause_time": 500,
				"show_flankers": true,
				"progress": 0.34444444444444444
			}
		},
		{
			"event": "training_block",
			"payload": {
				"training_trials": [
					{
						"word": [
							12,
							8,
							5,
							2,
							0
						],
						"object": 5
					},
					{
						"word": [
							12,
							8,
							3,
							1,
							0
						],
						"object": 1
					},
					{
						"word": [
							13,
							9,
							6,
							2,
							0
						],
						"object": 6
					},
					{
						"word": [
							13,
							9,
							4,
							1,
							0
						],
						"object": 2
					}
				],
				"test_trial": {
					"word": [
						11,
						7,
						5,
						2,
						0
					],
					"object": 4
				},
				"trial_time": 2000,
				"pause_time": 500,
				"show_flankers": true,
				"progress": 0.35555555555555557
			}
		},
		{
			"event": "training_block",
			"payload": {
				"training_trials": [
					{
						"word": [
							14,
							10,
							4,
							1,
							0
						],
						"object": 3
					},
					{
						"word": [
							14,
							10,
							6,
							2,
							0
						],
						"object": 7
					},
					{
						"word": [
							11,
							7,
							5,
							2,
							0
						],
						"object": 4
					},
					{
						"word": [
							11,
							7,
							3,
							1,
							0
						],
						"object": 0
					}
				],
				"test_trial": {
					"word": [
						13,
						9,
						4,
						1,
						0
					],
					"object": 2
				},
				"trial_time": 2000,
				"pause_time": 500,
				"show_flankers": true,
				"progress": 0.36666666666666664
			}
		},
		{
			"event": "training_block",
			"payload": {
				"training_trials": [
					{
						"word": [
							14,
							10,
							4,
							1,
							0
						],
						"object": 3
					},
					{
						"word": [
							14,
							10,
							6,
							2,
							0
						],
						"object": 7
					},
					{
						"word": [
							13,
							9,
							6,
							2,
							0
						],
						"object": 6
					},
					{
						"word": [
							11,
							7,
							5,
							2,
							0
						],
						"object": 4
					}
				],
				"test_trial": {
					"word": [
						13,
						9,
						6,
						2,
						0
					],
					"object": 6
				},
				"trial_time": 2000,
				"pause_time": 500,
				"show_flankers": true,
				"progress": 0.37777777777777777
			}
		},
		{
			"event": "training_block",
			"payload": {
				"training_trials": [
					{
						"word": [
							12,
							8,
							3,
							1,
							0
						],
						"object": 1
					},
					{
						"word": [
							11,
							7,
							3,
							1,
							0
						],
						"object": 0
					},
					{
						"word": [
							13,
							9,
							4,
							1,
							0
						],
						"object": 2
					},
					{
						"word": [
							12,
							8,
							5,
							2,
							0
						],
						"object": 5
					}
				],
				"test_trial": {
					"word": [
						12,
						8,
						5,
						2,
						0
					],
					"object": 5
				},
				"trial_time": 2000,
				"pause_time": 500,
				"show_flankers": true,
				"progress": 0.3888888888888889
			}
		},
		{
			"event": "training_block",
			"payload": {
				"training_trials": [
					{
						"word": [
							11,
							7,
							5,
							2,
							0
						],
						"object": 4
					},
					{
						"word": [
							14,
							10,
							6,
							2,
							0
						],
						"object": 7
					},
					{
						"word": [
							11,
							7,
							3,
							1,
							0
						],
						"object": 0
					},
					{
						"word": [
							12,
							8,
							3,
							1,
							0
						],
						"object": 1
					}
				],
				"test_trial": {
					"word": [
						11,
						7,
						3,
						1,
						0
					],
					"object": 0
				},
				"trial_time": 2000,
				"pause_time": 500,
				"show_flankers": true,
				"progress": 0.4
			}
		},
		{
			"event": "training_block",
			"payload": {
				"training_trials": [
					{
						"word": [
							14,
							10,
							4,
							1,
							0
						],
						"object": 3
					},
					{
						"word": [
							13,
							9,
							6,
							2,
							0
						],
						"object": 6
					},
					{
						"word": [
							12,
							8,
							5,
							2,
							0
						],
						"object": 5
					},
					{
						"word": [
							13,
							9,
							4,
							1,
							0
						],
						"object": 2
					}
				],
				"test_trial": {
					"word": [
						14,
						10,
						6,
						2,
						0
					],
					"object": 7
				},
				"trial_time": 2000,
				"pause_time": 500,
				"show_flankers": true,
				"progress": 0.4111111111111111
			}
		},
		{
			"event": "training_block",
			"payload": {
				"training_trials": [
					{
						"word": [
							12,
							8,
							5,
							2,
							0
						],
						"object": 5
					},
					{
						"word": [
							11,
							7,
							5,
							2,
							0
						],
						"object": 4
					},
					{
						"word": [
							11,
							7,
							3,
							1,
							0
						],
						"object": 0
					},
					{
						"word": [
							13,
							9,
							6,
							2,
							0
						],
						"object": 6
					}
				],
				"test_trial": {
					"word": [
						11,
						7,
						3,
						1,
						0
					],
					"object": 0
				},
				"trial_time": 2000,
				"pause_time": 500,
				"show_flankers": true,
				"progress": 0.4222222222222222
			}
		},
		{
			"event": "training_block",
			"payload": {
				"training_trials": [
					{
						"word": [
							14,
							10,
							4,
							1,
							0
						],
						"object": 3
					},
					{
						"word": [
							14,
							10,
							6,
							2,
							0
						],
						"object": 7
					},
					{
						"word": [
							13,
							9,
							4,
							1,
							0
						],
						"object": 2
					},
					{
						"word": [
							12,
							8,
							3,
							1,
							0
						],
						"object": 1
					}
				],
				"test_trial": {
					"word": [
						14,
						10,
						6,
						2,
						0
					],
					"object": 7
				},
				"trial_time": 2000,
				"pause_time": 500,
				"show_flankers": true,
				"progress": 0.43333333333333335
			}
		},
		{
			"event": "training_block",
			"payload": {
				"training_trials": [
					{
						"word": [
							12,
							8,
							5,
							2,
							0
						],
						"object": 5
					},
					{
						"word": [
							14,
							10,
							6,
							2,
							0
						],
						"object": 7
					},
					{
						"word": [
							12,
							8,
							3,
							1,
							0
						],
						"object": 1
					},
					{
						"word": [
							11,
							7,
							5,
							2,
							0
						],
						"object": 4
					}
				],
				"test_trial": {
					"word": [
						12,
						8,
						5,
						2,
						0
					],
					"object": 5
				},
				"trial_time": 2000,
				"pause_time": 500,
				"show_flankers": true,
				"progress": 0.4444444444444444
			}
		},
		{
			"event": "training_block",
			"payload": {
				"training_trials": [
					{
						"word": [
							13,
							9,
							6,
							2,
							0
						],
						"object": 6
					},
					{
						"word": [
							11,
							7,
							3,
							1,
							0
						],
						"object": 0
					},
					{
						"word": [
							13,
							9,
							4,
							1,
							0
						],
						"object": 2
					},
					{
						"word": [
							14,
							10,
							4,
							1,
							0
						],
						"object": 3
					}
				],
				"test_trial": {
					"word": [
						12,
						8,
						3,
						1,
						0
					],
					"object": 1
				},
				"trial_time": 2000,
				"pause_time": 500,
				"show_flankers": true,
				"progress": 0.45555555555555555
			}
		},
		{
			"event": "training_block",
			"payload": {
				"training_trials": [
					{
						"word": [
							11,
							7,
							3,
							1,
							0
						],
						"object": 0
					},
					{
						"word": [
							11,
							7,
							5,
							2,
							0
						],
						"object": 4
					},
					{
						"word": [
							13,
							9,
							4,
							1,
							0
						],
						"object": 2
					},
					{
						"word": [
							14,
							10,
							4,
							1,
							0
						],
						"object": 3
					}
				],
				"test_trial": {
					"word": [
						14,
						10,
						4,
						1,
						0
					],
					"object": 3
				},
				"trial_time": 2000,
				"pause_time": 500,
				"show_flankers": true,
				"progress": 0.4666666666666667
			}
		},
		{
			"event": "training_block",
			"payload": {
				"training_trials": [
					{
						"word": [
							12,
							8,
							3,
							1,
							0
						],
						"object": 1
					},
					{
						"word": [
							13,
							9,
							6,
							2,
							0
						],
						"object": 6
					},
					{
						"word": [
							12,
							8,
							5,
							2,
							0
						],
						"object": 5
					},
					{
						"word": [
							14,
							10,
							6,
							2,
							0
						],
						"object": 7
					}
				],
				"test_trial": {
					"word": [
						11,
						7,
						5,
						2,
						0
					],
					"object": 4
				},
				"trial_time": 2000,
				"pause_time": 500,
				"show_flankers": true,
				"progress": 0.4777777777777778
			}
		},
		{
			"event": "training_block",
			"payload": {
				"training_trials": [
					{
						"word": [
							12,
							8,
							5,
							2,
							0
						],
						"object": 5
					},
					{
						"word": [
							13,
							9,
							4,
							1,
							0
						],
						"object": 2
					},
					{
						"word": [
							14,
							10,
							6,
							2,
							0
						],
						"object": 7
					},
					{
						"word": [
							13,
							9,
							6,
							2,
							0
						],
						"object": 6
					}
				],
				"test_trial": {
					"word": [
						13,
						9,
						4,
						1,
						0
					],
					"object": 2
				},
				"trial_time": 2000,
				"pause_time": 500,
				"show_flankers": true,
				"progress": 0.4888888888888889
			}
		},
		{
			"event": "training_block",
			"payload": {
				"training_trials": [
					{
						"word": [
							11,
							7,
							5,
							2,
							0
						],
						"object": 4
					},
					{
						"word": [
							11,
							7,
							3,
							1,
							0
						],
						"object": 0
					},
					{
						"word": [
							14,
							10,
							4,
							1,
							0
						],
						"object": 3
					},
					{
						"word": [
							12,
							8,
							3,
							1,
							0
						],
						"object": 1
					}
				],
				"test_trial": {
					"word": [
						13,
						9,
						6,
						2,
						0
					],
					"object": 6
				},
				"trial_time": 2000,
				"pause_time": 500,
				"show_flankers": true,
				"progress": 0.5
			}
		},
		{
			"event": "training_block",
			"payload": {
				"training_trials": [
					{
						"word": [
							11,
							7,
							5,
							2,
							0
						],
						"object": 4
					},
					{
						"word": [
							11,
							7,
							3,
							1,
							0
						],
						"object": 0
					},
					{
						"word": [
							12,
							8,
							3,
							1,
							0
						],
						"object": 1
					},
					{
						"word": [
							13,
							9,
							6,
							2,
							0
						],
						"object": 6
					}
				],
				"test_trial": {
					"word": [
						11,
						7,
						3,
						1,
						0
					],
					"object": 0
				},
				"trial_time": 2000,
				"pause_time": 500,
				"show_flankers": true,
				"progress": 0.5111111111111111
			}
		},
		{
			"event": "training_block",
			"payload": {
				"training_trials": [
					{
						"word": [
							12,
							8,
							5,
							2,
							0
						],
						"object": 5
					},
					{
						"word": [
							14,
							10,
							6,
							2,
							0
						],
						"object": 7
					},
					{
						"word": [
							13,
							9,
							4,
							1,
							0
						],
						"object": 2
					},
					{
						"word": [
							14,
							10,
							4,
							1,
							0
						],
						"object": 3
					}
				],
				"test_trial": {
					"word": [
						12,
						8,
						3,
						1,
						0
					],
					"object": 1
				},
				"trial_time": 2000,
				"pause_time": 500,
				"show_flankers": true,
				"progress": 0.5222222222222223
			}
		},
		{
			"event": "training_block",
			"payload": {
				"training_trials": [
					{
						"word": [
							13,
							9,
							6,
							2,
							0
						],
						"object": 6
					},
					{
						"word": [
							12,
							8,
							5,
							2,
							0
						],
						"object": 5
					},
					{
						"word": [
							14,
							10,
							4,
							1,
							0
						],
						"object": 3
					},
					{
						"word": [
							11,
							7,
							5,
							2,
							0
						],
						"object": 4
					}
				],
				"test_trial": {
					"word": [
						12,
						8,
						5,
						2,
						0
					],
					"object": 5
				},
				"trial_time": 2000,
				"pause_time": 500,
				"show_flankers": true,
				"progress": 0.5333333333333333
			}
		},
		{
			"event": "training_block",
			"payload": {
				"training_trials": [
					{
						"word": [
							12,
							8,
							3,
							1,
							0
						],
						"object": 1
					},
					{
						"word": [
							14,
							10,
							6,
							2,
							0
						],
						"object": 7
					},
					{
						"word": [
							13,
							9,
							4,
							1,
							0
						],
						"object": 2
					},
					{
						"word": [
							11,
							7,
							3,
							1,
							0
						],
						"object": 0
					}
				],
				"test_trial": {
					"word": [
						11,
						7,
						5,
						2,
						0
					],
					"object": 4
				},
				"trial_time": 2000,
				"pause_time": 500,
				"show_flankers": true,
				"progress": 0.5444444444444444
			}
		},
		{
			"event": "training_block",
			"payload": {
				"training_trials": [
					{
						"word": [
							13,
							9,
							4,
							1,
							0
						],
						"object": 2
					},
					{
						"word": [
							11,
							7,
							3,
							1,
							0
						],
						"object": 0
					},
					{
						"word": [
							13,
							9,
							6,
							2,
							0
						],
						"object": 6
					},
					{
						"word": [
							14,
							10,
							4,
							1,
							0
						],
						"object": 3
					}
				],
				"test_trial": {
					"word": [
						14,
						10,
						4,
						1,
						0
					],
					"object": 3
				},
				"trial_time": 2000,
				"pause_time": 500,
				"show_flankers": true,
				"progress": 0.5555555555555556
			}
		},
		{
			"event": "training_block",
			"payload": {
				"training_trials": [
					{
						"word": [
							11,
							7,
							5,
							2,
							0
						],
						"object": 4
					},
					{
						"word": [
							14,
							10,
							6,
							2,
							0
						],
						"object": 7
					},
					{
						"word": [
							12,
							8,
							5,
							2,
							0
						],
						"object": 5
					},
					{
						"word": [
							12,
							8,
							3,
							1,
							0
						],
						"object": 1
					}
				],
				"test_trial": {
					"word": [
						14,
						10,
						6,
						2,
						0
					],
					"object": 7
				},
				"trial_time": 2000,
				"pause_time": 500,
				"show_flankers": true,
				"progress": 0.5666666666666667
			}
		},
		{
			"event": "training_block",
			"payload": {
				"training_trials": [
					{
						"word": [
							14,
							10,
							6,
							2,
							0
						],
						"object": 7
					},
					{
						"word": [
							12,
							8,
							3,
							1,
							0
						],
						"object": 1
					},
					{
						"word": [
							13,
							9,
							6,
							2,
							0
						],
						"object": 6
					},
					{
						"word": [
							14,
							10,
							4,
							1,
							0
						],
						"object": 3
					}
				],
				"test_trial": {
					"word": [
						13,
						9,
						6,
						2,
						0
					],
					"object": 6
				},
				"trial_time": 2000,
				"pause_time": 500,
				"show_flankers": true,
				"progress": 0.5777777777777777
			}
		},
		{
			"event": "training_block",
			"payload": {
				"training_trials": [
					{
						"word": [
							11,
							7,
							3,
							1,
							0
						],
						"object": 0
					},
					{
						"word": [
							11,
							7,
							5,
							2,
							0
						],
						"object": 4
					},
					{
						"word": [
							13,
							9,
							4,
							1,
							0
						],
						"object": 2
					},
					{
						"word": [
							12,
							8,
							5,
							2,
							0
						],
						"object": 5
					}
				],
				"test_trial": {
					"word": [
						13,
						9,
						4,
						1,
						0
					],
					"object": 2
				},
				"trial_time": 2000,
				"pause_time": 500,
				"show_flankers": true,
				"progress": 0.5888888888888889
			}
		},
		{
			"event": "training_block",
			"payload": {
				"training_trials": [
					{
						"word": [
							11,
							7,
							3,
							1,
							0
						],
						"object": 0
					},
					{
						"word": [
							12,
							8,
							3,
							1,
							0
						],
						"object": 1
					},
					{
						"word": [
							12,
							8,
							5,
							2,
							0
						],
						"object": 5
					},
					{
						"word": [
							14,
							10,
							6,
							2,
							0
						],
						"object": 7
					}
				],
				"test_trial": {
					"word": [
						12,
						8,
						5,
						2,
						0
					],
					"object": 5
				},
				"trial_time": 2000,
				"pause_time": 500,
				"show_flankers": true,
				"progress": 0.6
			}
		},
		{
			"event": "training_block",
			"payload": {
				"training_trials": [
					{
						"word": [
							13,
							9,
							4,
							1,
							0
						],
						"object": 2
					},
					{
						"word": [
							14,
							10,
							4,
							1,
							0
						],
						"object": 3
					},
					{
						"word": [
							13,
							9,
							6,
							2,
							0
						],
						"object": 6
					},
					{
						"word": [
							11,
							7,
							5,
							2,
							0
						],
						"object": 4
					}
				],
				"test_trial": {
					"word": [
						11,
						7,
						5,
						2,
						0
					],
					"object": 4
				},
				"trial_time": 2000,
				"pause_time": 500,
				"show_flankers": true,
				"progress": 0.6111111111111112
			}
		},
		{
			"event": "training_block",
			"payload": {
				"training_trials": [
					{
						"word": [
							13,
							9,
							4,
							1,
							0
						],
						"object": 2
					},
					{
						"word": [
							12,
							8,
							3,
							1,
							0
						],
						"object": 1
					},
					{
						"word": [
							11,
							7,
							5,
							2,
							0
						],
						"object": 4
					},
					{
						"word": [
							12,
							8,
							5,
							2,
							0
						],
						"object": 5
					}
				],
				"test_trial": {
					"word": [
						12,
						8,
						3,
						1,
						0
					],
					"object": 1
				},
				"trial_time": 2000,
				"pause_time": 500,
				"show_flankers": true,
				"progress": 0.6222222222222222
			}
		},
		{
			"event": "training_block",
			"payload": {
				"training_trials": [
					{
						"word": [
							11,
							7,
							3,
							1,
							0
						],
						"object": 0
					},
					{
						"word": [
							14,
							10,
							4,
							1,
							0
						],
						"object": 3
					},
					{
						"word": [
							13,
							9,
							6,
							2,
							0
						],
						"object": 6
					},
					{
						"word": [
							14,
							10,
							6,
							2,
							0
						],
						"object": 7
					}
				],
				"test_trial": {
					"word": [
						11,
						7,
						3,
						1,
						0
					],
					"object": 0
				},
				"trial_time": 2000,
				"pause_time": 500,
				"show_flankers": true,
				"progress": 0.6333333333333333
			}
		},
		{
			"event": "training_block",
			"payload": {
				"training_trials": [
					{
						"word": [
							13,
							9,
							6,
							2,
							0
						],
						"object": 6
					},
					{
						"word": [
							14,
							10,
							6,
							2,
							0
						],
						"object": 7
					},
					{
						"word": [
							14,
							10,
							4,
							1,
							0
						],
						"object": 3
					},
					{
						"word": [
							12,
							8,
							3,
							1,
							0
						],
						"object": 1
					}
				],
				"test_trial": {
					"word": [
						14,
						10,
						4,
						1,
						0
					],
					"object": 3
				},
				"trial_time": 2000,
				"pause_time": 500,
				"show_flankers": true,
				"progress": 0.6444444444444445
			}
		},
		{
			"event": "training_block",
			"payload": {
				"training_trials": [
					{
						"word": [
							11,
							7,
							3,
							1,
							0
						],
						"object": 0
					},
					{
						"word": [
							11,
							7,
							5,
							2,
							0
						],
						"object": 4
					},
					{
						"word": [
							12,
							8,
							5,
							2,
							0
						],
						"object": 5
					},
					{
						"word": [
							13,
							9,
							4,
							1,
							0
						],
						"object": 2
					}
				],
				"test_trial": {
					"word": [
						13,
						9,
						4,
						1,
						0
					],
					"object": 2
				},
				"trial_time": 2000,
				"pause_time": 500,
				"show_flankers": true,
				"progress": 0.6555555555555556
			}
		},
		{
			"event": "training_block",
			"payload": {
				"training_trials": [
					{
						"word": [
							14,
							10,
							6,
							2,
							0
						],
						"object": 7
					},
					{
						"word": [
							12,
							8,
							5,
							2,
							0
						],
						"object": 5
					},
					{
						"word": [
							14,
							10,
							4,
							1,
							0
						],
						"object": 3
					},
					{
						"word": [
							13,
							9,
							6,
							2,
							0
						],
						"object": 6
					}
				],
				"test_trial": {
					"word": [
						13,
						9,
						6,
						2,
						0
					],
					"object": 6
				},
				"trial_time": 2000,
				"pause_time": 500,
				"show_flankers": true,
				"progress": 0.6666666666666666
			}
		},
		{
			"event": "training_block",
			"payload": {
				"training_trials": [
					{
						"word": [
							13,
							9,
							4,
							1,
							0
						],
						"object": 2
					},
					{
						"word": [
							11,
							7,
							5,
							2,
							0
						],
						"object": 4
					},
					{
						"word": [
							12,
							8,
							3,
							1,
							0
						],
						"object": 1
					},
					{
						"word": [
							11,
							7,
							3,
							1,
							0
						],
						"object": 0
					}
				],
				"test_trial": {
					"word": [
						14,
						10,
						6,
						2,
						0
					],
					"object": 7
				},
				"trial_time": 2000,
				"pause_time": 500,
				"show_flankers": true,
				"progress": 0.6777777777777778
			}
		},
		{
			"event": "training_block",
			"payload": {
				"training_trials": [
					{
						"word": [
							12,
							8,
							5,
							2,
							0
						],
						"object": 5
					},
					{
						"word": [
							14,
							10,
							4,
							1,
							0
						],
						"object": 3
					},
					{
						"word": [
							12,
							8,
							3,
							1,
							0
						],
						"object": 1
					},
					{
						"word": [
							13,
							9,
							4,
							1,
							0
						],
						"object": 2
					}
				],
				"test_trial": {
					"word": [
						14,
						10,
						4,
						1,
						0
					],
					"object": 3
				},
				"trial_time": 2000,
				"pause_time": 500,
				"show_flankers": true,
				"progress": 0.6888888888888889
			}
		},
		{
			"event": "training_block",
			"payload": {
				"training_trials": [
					{
						"word": [
							11,
							7,
							5,
							2,
							0
						],
						"object": 4
					},
					{
						"word": [
							13,
							9,
							6,
							2,
							0
						],
						"object": 6
					},
					{
						"word": [
							11,
							7,
							3,
							1,
							0
						],
						"object": 0
					},
					{
						"word": [
							14,
							10,
							6,
							2,
							0
						],
						"object": 7
					}
				],
				"test_trial": {
					"word": [
						11,
						7,
						3,
						1,
						0
					],
					"object": 0
				},
				"trial_time": 2000,
				"pause_time": 500,
				"show_flankers": true,
				"progress": 0.7
			}
		},
		{
			"event": "training_block",
			"payload": {
				"training_trials": [
					{
						"word": [
							13,
							9,
							4,
							1,
							0
						],
						"object": 2
					},
					{
						"word": [
							14,
							10,
							4,
							1,
							0
						],
						"object": 3
					},
					{
						"word": [
							13,
							9,
							6,
							2,
							0
						],
						"object": 6
					},
					{
						"word": [
							12,
							8,
							5,
							2,
							0
						],
						"object": 5
					}
				],
				"test_trial": {
					"word": [
						11,
						7,
						5,
						2,
						0
					],
					"object": 4
				},
				"trial_time": 2000,
				"pause_time": 500,
				"show_flankers": true,
				"progress": 0.7111111111111111
			}
		},
		{
			"event": "training_block",
			"payload": {
				"training_trials": [
					{
						"word": [
							14,
							10,
							6,
							2,
							0
						],
						"object": 7
					},
					{
						"word": [
							11,
							7,
							5,
							2,
							0
						],
						"object": 4
					},
					{
						"word": [
							12,
							8,
							3,
							1,
							0
						],
						"object": 1
					},
					{
						"word": [
							11,
							7,
							3,
							1,
							0
						],
						"object": 0
					}
				],
				"test_trial": {
					"word": [
						12,
						8,
						3,
						1,
						0
					],
					"object": 1
				},
				"trial_time": 2000,
				"pause_time": 500,
				"show_flankers": true,
				"progress": 0.7222222222222222
			}
		},
		{
			"event": "training_block",
			"payload": {
				"training_trials": [
					{
						"word": [
							12,
							8,
							5,
							2,
							0
						],
						"object": 5
					},
					{
						"word": [
							12,
							8,
							3,
							1,
							0
						],
						"object": 1
					},
					{
						"word": [
							11,
							7,
							3,
							1,
							0
						],
						"object": 0
					},
					{
						"word": [
							11,
							7,
							5,
							2,
							0
						],
						"object": 4
					}
				],
				"test_trial": {
					"word": [
						13,
						9,
						6,
						2,
						0
					],
					"object": 6
				},
				"trial_time": 2000,
				"pause_time": 500,
				"show_flankers": true,
				"progress": 0.7333333333333333
			}
		},
		{
			"event": "training_block",
			"payload": {
				"training_trials": [
					{
						"word": [
							13,
							9,
							6,
							2,
							0
						],
						"object": 6
					},
					{
						"word": [
							14,
							10,
							6,
							2,
							0
						],
						"object": 7
					},
					{
						"word": [
							14,
							10,
							4,
							1,
							0
						],
						"object": 3
					},
					{
						"word": [
							13,
							9,
							4,
							1,
							0
						],
						"object": 2
					}
				],
				"test_trial": {
					"word": [
						14,
						10,
						6,
						2,
						0
					],
					"object": 7
				},
				"trial_time": 2000,
				"pause_time": 500,
				"show_flankers": true,
				"progress": 0.7444444444444445
			}
		},
		{
			"event": "training_block",
			"payload": {
				"training_trials": [
					{
						"word": [
							14,
							10,
							4,
							1,
							0
						],
						"object": 3
					},
					{
						"word": [
							11,
							7,
							5,
							2,
							0
						],
						"object": 4
					},
					{
						"word": [
							14,
							10,
							6,
							2,
							0
						],
						"object": 7
					},
					{
						"word": [
							11,
							7,
							3,
							1,
							0
						],
						"object": 0
					}
				],
				"test_trial": {
					"word": [
						13,
						9,
						4,
						1,
						0
					],
					"object": 2
				},
				"trial_time": 2000,
				"pause_time": 500,
				"show_flankers": true,
				"progress": 0.7555555555555555
			}
		},
		{
			"event": "training_block",
			"payload": {
				"training_trials": [
					{
						"word": [
							12,
							8,
							5,
							2,
							0
						],
						"object": 5
					},
					{
						"word": [
							13,
							9,
							4,
							1,
							0
						],
						"object": 2
					},
					{
						"word": [
							13,
							9,
							6,
							2,
							0
						],
						"object": 6
					},
					{
						"word": [
							12,
							8,
							3,
							1,
							0
						],
						"object": 1
					}
				],
				"test_trial": {
					"word": [
						12,
						8,
						5,
						2,
						0
					],
					"object": 5
				},
				"trial_time": 2000,
				"pause_time": 500,
				"show_flankers": true,
				"progress": 0.7666666666666667
			}
		},
		{
			"event": "test_instructions",
			"payload": {
				"instruction_time": 10000,
				"progress": 0.7777777777777778
			}
		},
		{
			"event": "ovp_test",
			"payload": {
				"word": [
					11,
					7,
					3,
					1,
					0
				],
				"object": 0,
				"fixation_position": 2,
				"reveal_time": 100,
				"delay_time": 2853,
				"pause_time": 500,
				"show_flankers": true,
				"progress": 0.8
			}
		},
		{
			"event": "ovp_test",
			"payload": {
				"word": [
					11,
					7,
					3,
					1,
					0
				],
				"object": 0,
				"fixation_position": 3,
				"reveal_time": 100,
				"delay_time": 1549,
				"pause_time": 500,
				"show_flankers": true,
				"progress": 0.8044444444444444
			}
		},
		{
			"event": "ovp_test",
			"payload": {
				"word": [
					14,
					10,
					6,
					2,
					0
				],
				"object": 7,
				"fixation_position": 0,
				"reveal_time": 100,
				"delay_time": 2554,
				"pause_time": 500,
				"show_flankers": true,
				"progress": 0.8088888888888889
			}
		},
		{
			"event": "ovp_test",
			"payload": {
				"word": [
					12,
					8,
					3,
					1,
					0
				],
				"object": 1,
				"fixation_position": 4,
				"reveal_time": 100,
				"delay_time": 2209,
				"pause_time": 500,
				"show_flankers": true,
				"progress": 0.8133333333333334
			}
		},
		{
			"event": "ovp_test",
			"payload": {
				"word": [
					14,
					10,
					4,
					1,
					0
				],
				"object": 3,
				"fixation_position": 3,
				"reveal_time": 100,
				"delay_time": 2100,
				"pause_time": 500,
				"show_flankers": true,
				"progress": 0.8177777777777778
			}
		},
		{
			"event": "ovp_test",
			"payload": {
				"word": [
					13,
					9,
					6,
					2,
					0
				],
				"object": 6,
				"fixation_position": 3,
				"reveal_time": 100,
				"delay_time": 2691,
				"pause_time": 500,
				"show_flankers": true,
				"progress": 0.8222222222222222
			}
		},
		{
			"event": "ovp_test",
			"payload": {
				"word": [
					14,
					10,
					4,
					1,
					0
				],
				"object": 3,
				"fixation_position": 2,
				"reveal_time": 100,
				"delay_time": 1330,
				"pause_time": 500,
				"show_flankers": true,
				"progress": 0.8266666666666667
			}
		},
		{
			"event": "ovp_test",
			"payload": {
				"word": [
					12,
					8,
					3,
					1,
					0
				],
				"object": 1,
				"fixation_position": 0,
				"reveal_time": 100,
				"delay_time": 2607,
				"pause_time": 500,
				"show_flankers": true,
				"progress": 0.8311111111111111
			}
		},
		{
			"event": "ovp_test",
			"payload": {
				"word": [
					12,
					8,
					5,
					2,
					0
				],
				"object": 5,
				"fixation_position": 1,
				"reveal_time": 100,
				"delay_time": 1280,
				"pause_time": 500,
				"show_flankers": true,
				"progress": 0.8355555555555556
			}
		},
		{
			"event": "ovp_test",
			"payload": {
				"word": [
					11,
					7,
					5,
					2,
					0
				],
				"object": 4,
				"fixation_position": 1,
				"reveal_time": 100,
				"delay_time": 1589,
				"pause_time": 500,
				"show_flankers": true,
				"progress": 0.84
			}
		},
		{
			"event": "ovp_test",
			"payload": {
				"word": [
					12,
					8,
					5,
					2,
					0
				],
				"object": 5,
				"fixation_position": 3,
				"reveal_time": 100,
				"delay_time": 1697,
				"pause_time": 500,
				"show_flankers": true,
				"progress": 0.8444444444444444
			}
		},
		{
			"event": "ovp_test",
			"payload": {
				"word": [
					11,
					7,
					5,
					2,
					0
				],
				"object": 4,
				"fixation_position": 0,
				"reveal_time": 100,
				"delay_time": 2168,
				"pause_time": 500,
				"show_flankers": true,
				"progress": 0.8488888888888889
			}
		},
		{
			"event": "ovp_test",
			"payload": {
				"word": [
					14,
					10,
					4,
					1,
					0
				],
				"object": 3,
				"fixation_position": 4,
				"reveal_time": 100,
				"delay_time": 2220,
				"pause_time": 500,
				"show_flankers": true,
				"progress": 0.8533333333333334
			}
		},
		{
			"event": "ovp_test",
			"payload": {
				"word": [
					12,
					8,
					3,
					1,
					0
				],
				"object": 1,
				"fixation_position": 3,
				"reveal_time": 100,
				"delay_time": 1955,
				"pause_time": 500,
				"show_flankers": true,
				"progress": 0.8577777777777778
			}
		},
		{
			"event": "ovp_test",
			"payload": {
				"word": [
					12,
					8,
					5,
					2,
					0
				],
				"object": 5,
				"fixation_position": 0,
				"reveal_time": 100,
				"delay_time": 2022,
				"pause_time": 500,
				"show_flankers": true,
				"progress": 0.8622222222222222
			}
		},
		{
			"event": "ovp_test",
			"payload": {
				"word": [
					11,
					7,
					3,
					1,
					0
				],
				"object": 0,
				"fixation_position": 4,
				"reveal_time": 100,
				"delay_time": 2741,
				"pause_time": 500,
				"show_flankers": true,
				"progress": 0.8666666666666667
			}
		},
		{
			"event": "ovp_test",
			"payload": {
				"word": [
					14,
					10,
					6,
					2,
					0
				],
				"object": 7,
				"fixation_position": 2,
				"reveal_time": 100,
				"delay_time": 1416,
				"pause_time": 500,
				"show_flankers": true,
				"progress": 0.8711111111111111
			}
		},
		{
			"event": "ovp_test",
			"payload": {
				"word": [
					13,
					9,
					6,
					2,
					0
				],
				"object": 6,
				"fixation_position": 4,
				"reveal_time": 100,
				"delay_time": 2357,
				"pause_time": 500,
				"show_flankers": true,
				"progress": 0.8755555555555555
			}
		},
		{
			"event": "ovp_test",
			"payload": {
				"word": [
					14,
					10,
					6,
					2,
					0
				],
				"object": 7,
				"fixation_position": 3,
				"reveal_time": 100,
				"delay_time": 2872,
				"pause_time": 500,
				"show_flankers": true,
				"progress": 0.88
			}
		},
		{
			"event": "ovp_test",
			"payload": {
				"word": [
					11,
					7,
					5,
					2,
					0
				],
				"object": 4,
				"fixation_position": 2,
				"reveal_time": 100,
				"delay_time": 2351,
				"pause_time": 500,
				"show_flankers": true,
				"progress": 0.8844444444444445
			}
		},
		{
			"event": "ovp_test",
			"payload": {
				"word": [
					13,
					9,
					6,
					2,
					0
				],
				"object": 6,
				"fixation_position": 0,
				"reveal_time": 100,
				"delay_time": 2639,
				"pause_time": 500,
				"show_flankers": true,
				"progress": 0.8888888888888888
			}
		},
		{
			"event": "ovp_test",
			"payload": {
				"word": [
					12,
					8,
					5,
					2,
					0
				],
				"object": 5,
				"fixation_position": 4,
				"reveal_time": 100,
				"delay_time": 1544,
				"pause_time": 500,
				"show_flankers": true,
				"progress": 0.8933333333333333
			}
		},
		{
			"event": "ovp_test",
			"payload": {
				"word": [
					11,
					7,
					5,
					2,
					0
				],
				"object": 4,
				"fixation_position": 4,
				"reveal_time": 100,
				"delay_time": 2145,
				"pause_time": 500,
				"show_flankers": true,
				"progress": 0.8977777777777778
			}
		},
		{
			"event": "ovp_test",
			"payload": {
				"word": [
					14,
					10,
					6,
					2,
					0
				],
				"object": 7,
				"fixation_position": 1,
				"reveal_time": 100,
				"delay_time": 2672,
				"pause_time": 500,
				"show_flankers": true,
				"progress": 0.9022222222222223
			}
		},
		{
			"event": "ovp_test",
			"payload": {
				"word": [
					12,
					8,
					3,
					1,
					0
				],
				"object": 1,
				"fixation_position": 2,
				"reveal_time": 100,
				"delay_time": 2840,
				"pause_time": 500,
				"show_flankers": true,
				"progress": 0.9066666666666666
			}
		},
		{
			"event": "ovp_test",
			"payload": {
				"word": [
					14,
					10,
					6,
					2,
					0
				],
				"object": 7,
				"fixation_position": 4,
				"reveal_time": 100,
				"delay_time": 1553,
				"pause_time": 500,
				"show_flankers": true,
				"progress": 0.9111111111111111
			}
		},
		{
			"event": "ovp_test",
			"payload": {
				"word": [
					14,
					10,
					4,
					1,
					0
				],
				"object": 3,
				"fixation_position": 1,
				"reveal_time": 100,
				"delay_time": 2764,
				"pause_time": 500,
				"show_flankers": true,
				"progress": 0.9155555555555556
			}
		},
		{
			"event": "ovp_test",
			"payload": {
				"word": [
					11,
					7,
					3,
					1,
					0
				],
				"object": 0,
				"fixation_position": 0,
				"reveal_time": 100,
				"delay_time": 1163,
				"pause_time": 500,
				"show_flankers": true,
				"progress": 0.92
			}
		},
		{
			"event": "ovp_test",
			"payload": {
				"word": [
					13,
					9,
					4,
					1,
					0
				],
				"object": 2,
				"fixation_position": 4,
				"reveal_time": 100,
				"delay_time": 2661,
				"pause_time": 500,
				"show_flankers": true,
				"progress": 0.9244444444444444
			}
		},
		{
			"event": "ovp_test",
			"payload": {
				"word": [
					13,
					9,
					6,
					2,
					0
				],
				"object": 6,
				"fixation_position": 2,
				"reveal_time": 100,
				"delay_time": 2303,
				"pause_time": 500,
				"show_flankers": true,
				"progress": 0.9288888888888889
			}
		},
		{
			"event": "ovp_test",
			"payload": {
				"word": [
					14,
					10,
					4,
					1,
					0
				],
				"object": 3,
				"fixation_position": 0,
				"reveal_time": 100,
				"delay_time": 2746,
				"pause_time": 500,
				"show_flankers": true,
				"progress": 0.9333333333333333
			}
		},
		{
			"event": "ovp_test",
			"payload": {
				"word": [
					11,
					7,
					3,
					1,
					0
				],
				"object": 0,
				"fixation_position": 1,
				"reveal_time": 100,
				"delay_time": 1830,
				"pause_time": 500,
				"show_flankers": true,
				"progress": 0.9377777777777778
			}
		},
		{
			"event": "ovp_test",
			"payload": {
				"word": [
					13,
					9,
					4,
					1,
					0
				],
				"object": 2,
				"fixation_position": 3,
				"reveal_time": 100,
				"delay_time": 2537,
				"pause_time": 500,
				"show_flankers": true,
				"progress": 0.9422222222222222
			}
		},
		{
			"event": "ovp_test",
			"payload": {
				"word": [
					12,
					8,
					5,
					2,
					0
				],
				"object": 5,
				"fixation_position": 2,
				"reveal_time": 100,
				"delay_time": 1264,
				"pause_time": 500,
				"show_flankers": true,
				"progress": 0.9466666666666667
			}
		},
		{
			"event": "ovp_test",
			"payload": {
				"word": [
					13,
					9,
					6,
					2,
					0
				],
				"object": 6,
				"fixation_position": 1,
				"reveal_time": 100,
				"delay_time": 1215,
				"pause_time": 500,
				"show_flankers": true,
				"progress": 0.9511111111111111
			}
		},
		{
			"event": "ovp_test",
			"payload": {
				"word": [
					13,
					9,
					4,
					1,
					0
				],
				"object": 2,
				"fixation_position": 2,
				"reveal_time": 100,
				"delay_time": 2631,
				"pause_time": 500,
				"show_flankers": true,
				"progress": 0.9555555555555556
			}
		},
		{
			"event": "ovp_test",
			"payload": {
				"word": [
					11,
					7,
					5,
					2,
					0
				],
				"object": 4,
				"fixation_position": 3,
				"reveal_time": 100,
				"delay_time": 2020,
				"pause_time": 500,
				"show_flankers": true,
				"progress": 0.96
			}
		},
		{
			"event": "ovp_test",
			"payload": {
				"word": [
					13,
					9,
					4,
					1,
					0
				],
				"object": 2,
				"fixation_position": 0,
				"reveal_time": 100,
				"delay_time": 1165,
				"pause_time": 500,
				"show_flankers": true,
				"progress": 0.9644444444444444
			}
		},
		{
			"event": "ovp_test",
			"payload": {
				"word": [
					12,
					8,
					3,
					1,
					0
				],
				"object": 1,
				"fixation_position": 1,
				"reveal_time": 100,
				"delay_time": 1034,
				"pause_time": 500,
				"show_flankers": true,
				"progress": 0.9688888888888889
			}
		},
		{
			"event": "ovp_test",
			"payload": {
				"word": [
					13,
					9,
					4,
					1,
					0
				],
				"object": 2,
				"fixation_position": 1,
				"reveal_time": 100,
				"delay_time": 2176,
				"pause_time": 500,
				"show_flankers": true,
				"progress": 0.9733333333333334
			}
		},
		{
			"event": "questionnaire",
			"payload": {
				"progress": 0.9777777777777777
			}
		},
		{
			"event": "end_of_experiment",
			"payload": {
				"return_url": "https://app.prolific.co/submissions/complete?cc=66CC8E40",
				"basic_pay": 300,
				"progress": 1
			}
		}
	],
	"sequence_position": 110,
	"responses": [
		{
			"test_type": "mini_test",
			"object": 7,
			"selected_object": 1,
			"reaction_time": 3589,
			"time": 1622735605
		},
		{
			"test_type": "mini_test",
			"object": 4,
			"selected_object": 0,
			"reaction_time": 2068,
			"time": 1622735616
		},
		{
			"test_type": "mini_test",
			"object": 3,
			"selected_object": 5,
			"reaction_time": 1810,
			"time": 1622735628
		},
		{
			"test_type": "mini_test",
			"object": 2,
			"selected_object": 4,
			"reaction_time": 18382,
			"time": 1622735657
		},
		{
			"test_type": "mini_test",
			"object": 1,
			"selected_object": 5,
			"reaction_time": 11624,
			"time": 1622735679
		},
		{
			"test_type": "mini_test",
			"object": 6,
			"selected_object": 1,
			"reaction_time": 1690,
			"time": 1622735690
		},
		{
			"test_type": "mini_test",
			"object": 0,
			"selected_object": 4,
			"reaction_time": 17169,
			"time": 1622735717
		},
		{
			"test_type": "mini_test",
			"object": 5,
			"selected_object": 4,
			"reaction_time": 10784,
			"time": 1622735737
		},
		{
			"test_type": "mini_test",
			"object": 5,
			"selected_object": 1,
			"reaction_time": 1148,
			"time": 1622735750
		},
		{
			"test_type": "mini_test",
			"object": 0,
			"selected_object": 2,
			"reaction_time": 942,
			"time": 1622735761
		},
		{
			"test_type": "mini_test",
			"object": 2,
			"selected_object": 4,
			"reaction_time": 2042,
			"time": 1622735772
		},
		{
			"test_type": "mini_test",
			"object": 6,
			"selected_object": 6,
			"reaction_time": 1923,
			"time": 1622735784
		},
		{
			"test_type": "mini_test",
			"object": 1,
			"selected_object": 4,
			"reaction_time": 23862,
			"time": 1622735820
		},
		{
			"test_type": "mini_test",
			"object": 4,
			"selected_object": 5,
			"reaction_time": 1988,
			"time": 1622735832
		},
		{
			"test_type": "mini_test",
			"object": 7,
			"selected_object": 0,
			"reaction_time": 1494,
			"time": 1622735843
		},
		{
			"test_type": "mini_test",
			"object": 3,
			"selected_object": 4,
			"reaction_time": 174797,
			"time": 1622736027
		},
		{
			"test_type": "mini_test",
			"object": 7,
			"selected_object": 4,
			"reaction_time": 1301,
			"time": 1622736038
		},
		{
			"test_type": "mini_test",
			"object": 2,
			"selected_object": 4,
			"reaction_time": 995,
			"time": 1622736048
		},
		{
			"test_type": "mini_test",
			"object": 1,
			"selected_object": 4,
			"reaction_time": 479,
			"time": 1622736059
		},
		{
			"test_type": "mini_test",
			"object": 3,
			"selected_object": 7,
			"reaction_time": 2077,
			"time": 1622736070
		},
		{
			"test_type": "mini_test",
			"object": 0,
			"selected_object": 4,
			"reaction_time": 144156,
			"time": 1622736224
		},
		{
			"test_type": "mini_test",
			"object": 5,
			"selected_object": 5,
			"reaction_time": 1089,
			"time": 1622736235
		},
		{
			"test_type": "mini_test",
			"object": 6,
			"selected_object": 4,
			"reaction_time": 114533,
			"time": 1622736359
		},
		{
			"test_type": "mini_test",
			"object": 4,
			"selected_object": 4,
			"reaction_time": 1194,
			"time": 1622736370
		},
		{
			"test_type": "mini_test",
			"object": 3,
			"selected_object": 5,
			"reaction_time": 1635,
			"time": 1622736381
		},
		{
			"test_type": "mini_test",
			"object": 1,
			"selected_object": 6,
			"reaction_time": 1125,
			"time": 1622736391
		},
		{
			"test_type": "mini_test",
			"object": 4,
			"selected_object": 3,
			"reaction_time": 2739,
			"time": 1622736404
		},
		{
			"test_type": "mini_test",
			"object": 2,
			"selected_object": 3,
			"reaction_time": 11026,
			"time": 1622736424
		},
		{
			"test_type": "mini_test",
			"object": 6,
			"selected_object": 1,
			"reaction_time": 66309,
			"time": 1622736500
		},
		{
			"test_type": "mini_test",
			"object": 5,
			"selected_object": 0,
			"reaction_time": 97632,
			"time": 1622736608
		},
		{
			"test_type": "mini_test",
			"object": 0,
			"selected_object": 1,
			"reaction_time": 1353,
			"time": 1622736618
		},
		{
			"test_type": "mini_test",
			"object": 7,
			"selected_object": 3,
			"reaction_time": 5261,
			"time": 1622736633
		},
		{
			"test_type": "mini_test",
			"object": 0,
			"selected_object": 4,
			"reaction_time": 92839,
			"time": 1622736736
		},
		{
			"test_type": "mini_test",
			"object": 7,
			"selected_object": 1,
			"reaction_time": 738,
			"time": 1622736746
		},
		{
			"test_type": "mini_test",
			"object": 5,
			"selected_object": 4,
			"reaction_time": 285221,
			"time": 1622737041
		},
		{
			"test_type": "mini_test",
			"object": 1,
			"selected_object": 4,
			"reaction_time": 7168,
			"time": 1622737058
		},
		{
			"test_type": "mini_test",
			"object": 3,
			"selected_object": 4,
			"reaction_time": 2556,
			"time": 1622737072
		},
		{
			"test_type": "mini_test",
			"object": 4,
			"selected_object": 6,
			"reaction_time": 2908,
			"time": 1622737084
		},
		{
			"test_type": "mini_test",
			"object": 2,
			"selected_object": 4,
			"reaction_time": 463,
			"time": 1622737094
		},
		{
			"test_type": "mini_test",
			"object": 6,
			"selected_object": 0,
			"reaction_time": 77711,
			"time": 1622737182
		},
		{
			"test_type": "mini_test",
			"object": 0,
			"selected_object": 3,
			"reaction_time": 998,
			"time": 1622737192
		},
		{
			"test_type": "mini_test",
			"object": 1,
			"selected_object": 1,
			"reaction_time": 107447,
			"time": 1622737309
		},
		{
			"test_type": "mini_test",
			"object": 5,
			"selected_object": 1,
			"reaction_time": 715,
			"time": 1622737319
		},
		{
			"test_type": "mini_test",
			"object": 4,
			"selected_object": 0,
			"reaction_time": 7798,
			"time": 1622737337
		},
		{
			"test_type": "mini_test",
			"object": 3,
			"selected_object": 0,
			"reaction_time": 49335,
			"time": 1622737396
		},
		{
			"test_type": "mini_test",
			"object": 7,
			"selected_object": 0,
			"reaction_time": 10212,
			"time": 1622737416
		},
		{
			"test_type": "mini_test",
			"object": 6,
			"selected_object": 2,
			"reaction_time": 3463,
			"time": 1622737429
		},
		{
			"test_type": "mini_test",
			"object": 2,
			"selected_object": 4,
			"reaction_time": 268774,
			"time": 1622737707
		},
		{
			"test_type": "mini_test",
			"object": 5,
			"selected_object": 3,
			"reaction_time": 885,
			"time": 1622737718
		},
		{
			"test_type": "mini_test",
			"object": 4,
			"selected_object": 5,
			"reaction_time": 540,
			"time": 1622737728
		},
		{
			"test_type": "mini_test",
			"object": 1,
			"selected_object": 7,
			"reaction_time": 3694,
			"time": 1622737741
		},
		{
			"test_type": "mini_test",
			"object": 0,
			"selected_object": 4,
			"reaction_time": 7049,
			"time": 1622737758
		},
		{
			"test_type": "mini_test",
			"object": 3,
			"selected_object": 3,
			"reaction_time": 908,
			"time": 1622737768
		},
		{
			"test_type": "mini_test",
			"object": 2,
			"selected_object": 5,
			"reaction_time": 881,
			"time": 1622737779
		},
		{
			"test_type": "mini_test",
			"object": 6,
			"selected_object": 0,
			"reaction_time": 1541,
			"time": 1622737790
		},
		{
			"test_type": "mini_test",
			"object": 7,
			"selected_object": 3,
			"reaction_time": 992,
			"time": 1622737800
		},
		{
			"test_type": "mini_test",
			"object": 3,
			"selected_object": 3,
			"reaction_time": 12588,
			"time": 1622737823
		},
		{
			"test_type": "mini_test",
			"object": 0,
			"selected_object": 4,
			"reaction_time": 2782,
			"time": 1622737835
		},
		{
			"test_type": "mini_test",
			"object": 4,
			"selected_object": 5,
			"reaction_time": 820,
			"time": 1622737845
		},
		{
			"test_type": "mini_test",
			"object": 1,
			"selected_object": 6,
			"reaction_time": 649,
			"time": 1622737856
		},
		{
			"test_type": "mini_test",
			"object": 6,
			"selected_object": 0,
			"reaction_time": 869,
			"time": 1622737866
		},
		{
			"test_type": "mini_test",
			"object": 7,
			"selected_object": 3,
			"reaction_time": 5455,
			"time": 1622737881
		},
		{
			"test_type": "mini_test",
			"object": 2,
			"selected_object": 4,
			"reaction_time": 239924,
			"time": 1622738131
		},
		{
			"test_type": "mini_test",
			"object": 5,
			"selected_object": 6,
			"reaction_time": 1720,
			"time": 1622738142
		},
		{
			"test_type": "ovp_test",
			"fixation_position": 2,
			"object": 0,
			"selected_object": 1,
			"reaction_time": 4248,
			"time": 1622738180
		},
		{
			"test_type": "ovp_test",
			"fixation_position": 3,
			"object": 0,
			"selected_object": 4,
			"reaction_time": 2980,
			"time": 1622738185
		},
		{
			"test_type": "ovp_test",
			"fixation_position": 0,
			"object": 7,
			"selected_object": 4,
			"reaction_time": 12196,
			"time": 1622738201
		},
		{
			"test_type": "ovp_test",
			"fixation_position": 4,
			"object": 1,
			"selected_object": 2,
			"reaction_time": 4055,
			"time": 1622738209
		},
		{
			"test_type": "ovp_test",
			"fixation_position": 3,
			"object": 3,
			"selected_object": 0,
			"reaction_time": 1308,
			"time": 1622738213
		},
		{
			"test_type": "ovp_test",
			"fixation_position": 3,
			"object": 6,
			"selected_object": 6,
			"reaction_time": 11666,
			"time": 1622738229
		},
		{
			"test_type": "ovp_test",
			"fixation_position": 2,
			"object": 3,
			"selected_object": 7,
			"reaction_time": 2156,
			"time": 1622738236
		},
		{
			"test_type": "ovp_test",
			"fixation_position": 0,
			"object": 1,
			"selected_object": 0,
			"reaction_time": 1397,
			"time": 1622738241
		},
		{
			"test_type": "ovp_test",
			"fixation_position": 1,
			"object": 5,
			"selected_object": 0,
			"reaction_time": 12069,
			"time": 1622738256
		},
		{
			"test_type": "ovp_test",
			"fixation_position": 1,
			"object": 4,
			"selected_object": 4,
			"reaction_time": 11702,
			"time": 1622738270
		},
		{
			"test_type": "ovp_test",
			"fixation_position": 3,
			"object": 5,
			"selected_object": 4,
			"reaction_time": 84049,
			"time": 1622738357
		},
		{
			"test_type": "ovp_test",
			"fixation_position": 0,
			"object": 4,
			"selected_object": 0,
			"reaction_time": 15781,
			"time": 1622738376
		},
		{
			"test_type": "ovp_test",
			"fixation_position": 4,
			"object": 3,
			"selected_object": 1,
			"reaction_time": 3934,
			"time": 1622738384
		},
		{
			"test_type": "ovp_test",
			"fixation_position": 3,
			"object": 1,
			"selected_object": 5,
			"reaction_time": 239690,
			"time": 1622738627
		},
		{
			"test_type": "ovp_test",
			"fixation_position": 0,
			"object": 5,
			"selected_object": 1,
			"reaction_time": 352,
			"time": 1622738630
		},
		{
			"test_type": "ovp_test",
			"fixation_position": 4,
			"object": 0,
			"selected_object": 2,
			"reaction_time": 755,
			"time": 1622738635
		},
		{
			"test_type": "ovp_test",
			"fixation_position": 2,
			"object": 7,
			"selected_object": 7,
			"reaction_time": 746,
			"time": 1622738638
		},
		{
			"test_type": "ovp_test",
			"fixation_position": 4,
			"object": 6,
			"selected_object": 0,
			"reaction_time": 438,
			"time": 1622738642
		},
		{
			"test_type": "ovp_test",
			"fixation_position": 3,
			"object": 7,
			"selected_object": 1,
			"reaction_time": 1514,
			"time": 1622738648
		},
		{
			"test_type": "ovp_test",
			"fixation_position": 2,
			"object": 4,
			"selected_object": 4,
			"reaction_time": 6431,
			"time": 1622738658
		},
		{
			"test_type": "ovp_test",
			"fixation_position": 0,
			"object": 6,
			"selected_object": 0,
			"reaction_time": 546,
			"time": 1622738662
		},
		{
			"test_type": "ovp_test",
			"fixation_position": 4,
			"object": 5,
			"selected_object": 2,
			"reaction_time": 4785,
			"time": 1622738669
		},
		{
			"test_type": "ovp_test",
			"fixation_position": 4,
			"object": 4,
			"selected_object": 7,
			"reaction_time": 748,
			"time": 1622738673
		},
		{
			"test_type": "ovp_test",
			"fixation_position": 1,
			"object": 7,
			"selected_object": 0,
			"reaction_time": 1879,
			"time": 1622738679
		},
		{
			"test_type": "ovp_test",
			"fixation_position": 2,
			"object": 1,
			"selected_object": 4,
			"reaction_time": 575,
			"time": 1622738684
		},
		{
			"test_type": "ovp_test",
			"fixation_position": 4,
			"object": 7,
			"selected_object": 1,
			"reaction_time": 6937,
			"time": 1622738693
		},
		{
			"test_type": "ovp_test",
			"fixation_position": 1,
			"object": 3,
			"selected_object": 4,
			"reaction_time": 6767,
			"time": 1622738704
		},
		{
			"test_type": "ovp_test",
			"fixation_position": 0,
			"object": 0,
			"selected_object": 5,
			"reaction_time": 5863,
			"time": 1622738712
		},
		{
			"test_type": "ovp_test",
			"fixation_position": 4,
			"object": 2,
			"selected_object": 6,
			"reaction_time": 759,
			"time": 1622738717
		},
		{
			"test_type": "ovp_test",
			"fixation_position": 2,
			"object": 6,
			"selected_object": 6,
			"reaction_time": 997,
			"time": 1622738721
		},
		{
			"test_type": "ovp_test",
			"fixation_position": 0,
			"object": 3,
			"selected_object": 0,
			"reaction_time": 2217,
			"time": 1622738728
		},
		{
			"test_type": "ovp_test",
			"fixation_position": 1,
			"object": 0,
			"selected_object": 3,
			"reaction_time": 1811,
			"time": 1622738732
		},
		{
			"test_type": "ovp_test",
			"fixation_position": 3,
			"object": 2,
			"selected_object": 0,
			"reaction_time": 2570,
			"time": 1622738739
		},
		{
			"test_type": "ovp_test",
			"fixation_position": 2,
			"object": 5,
			"selected_object": 2,
			"reaction_time": 677,
			"time": 1622738742
		},
		{
			"test_type": "ovp_test",
			"fixation_position": 1,
			"object": 6,
			"selected_object": 4,
			"reaction_time": 1036,
			"time": 1622738745
		},
		{
			"test_type": "ovp_test",
			"fixation_position": 2,
			"object": 2,
			"selected_object": 5,
			"reaction_time": 1874,
			"time": 1622738751
		},
		{
			"test_type": "ovp_test",
			"fixation_position": 3,
			"object": 4,
			"selected_object": 6,
			"reaction_time": 1283,
			"time": 1622738755
		},
		{
			"test_type": "ovp_test",
			"fixation_position": 0,
			"object": 2,
			"selected_object": 7,
			"reaction_time": 1011,
			"time": 1622738760
		},
		{
			"test_type": "ovp_test",
			"fixation_position": 1,
			"object": 1,
			"selected_object": 6,
			"reaction_time": 1275,
			"time": 1622738764
		},
		{
			"test_type": "ovp_test",
			"fixation_position": 1,
			"object": 2,
			"selected_object": 4,
			"reaction_time": 750,
			"time": 1622738768
		}
	],
	"size_selection": 15,
	"basic_pay": 300,
	"total_bonus": 11,
	"comments": "I had some issues learnign the language as I could not understand the patterns",
	"first_language": "Portuguese",
	"other_languages": [
		"English"
	]
}